django_url_prefixer/__init__.py
django_url_prefixer/admin.py
django_url_prefixer/apps.py
django_url_prefixer/middleware.py
django_url_prefixer/models.py
django_url_prefixer/tests.py
django_url_prefixer/views.py
django_url_prefixer/migrations/__init__.py
django_url_prefixer-0.1.0.dist-info/LICENSE
django_url_prefixer-0.1.0.dist-info/METADATA
django_url_prefixer-0.1.0.dist-info/WHEEL
django_url_prefixer-0.1.0.dist-info/top_level.txt
django_url_prefixer-0.1.0.dist-info/RECORD
